soccer_twos/__init__.py
soccer_twos/agent_interface.py
soccer_twos/evaluate.py
soccer_twos/package.py
soccer_twos/side_channels.py
soccer_twos/utils.py
soccer_twos/watch.py
soccer_twos/wrappers.py
soccer_twos-0.1.14.dist-info/LICENSE
soccer_twos-0.1.14.dist-info/METADATA
soccer_twos-0.1.14.dist-info/WHEEL
soccer_twos-0.1.14.dist-info/top_level.txt
soccer_twos-0.1.14.dist-info/RECORD
