Metadata-Version: 2.1
Name: soccer-twos
Version: 0.1.14
Summary: A pre-compiled soccer-twos (Unity ML Agents) environment with a nice visualizer.
Home-page: https://github.com/bryanoliveira/soccer-twos-env
Author: Bryan L M Oliveira
Author-email: bryanlmoliveira@gmail.com
Project-URL: Bug Tracker, https://github.com/bryanoliveira/soccer-twos-env/issues
Classifier: Development Status :: 4 - Beta
Classifier: Programming Language :: Python :: 3
Classifier: License :: OSI Approved :: MIT License
Classifier: Operating System :: POSIX :: Linux
Classifier: Operating System :: Microsoft :: Windows
Classifier: Operating System :: MacOS
Classifier: Topic :: Games/Entertainment :: Simulation
Classifier: Topic :: Scientific/Engineering :: Artificial Intelligence
Requires-Python: >=3.6
License-File: LICENSE
Requires-Dist: gym (==0.19.0)
Requires-Dist: gym-unity (==0.27.0)
Requires-Dist: mlagents (==0.27.0)
Requires-Dist: mlagents-envs (==0.27.0)
